SALib/__init__.py
SALib/analyze/__init__.py
SALib/analyze/common_args.py
SALib/analyze/delta.py
SALib/analyze/dgsm.py
SALib/analyze/discrepancy.py
SALib/analyze/enhanced_hdmr.py
SALib/analyze/fast.py
SALib/analyze/ff.py
SALib/analyze/hdmr.py
SALib/analyze/morris.py
SALib/analyze/pawn.py
SALib/analyze/rbd_fast.py
SALib/analyze/rsa.py
SALib/analyze/sobol.py
SALib/plotting/__init__.py
SALib/plotting/bar.py
SALib/plotting/hdmr.py
SALib/plotting/heatmap.py
SALib/plotting/morris.py
SALib/sample/__init__.py
SALib/sample/common_args.py
SALib/sample/directions.py
SALib/sample/fast_sampler.py
SALib/sample/ff.py
SALib/sample/finite_diff.py
SALib/sample/latin.py
SALib/sample/saltelli.py
SALib/sample/sobol.py
SALib/sample/sobol_sequence.py
SALib/sample/morris/__init__.py
SALib/sample/morris/brute.py
SALib/sample/morris/local.py
SALib/sample/morris/morris.py
SALib/sample/morris/strategy.py
SALib/scripts/__init__.py
SALib/scripts/salib.bat
SALib/scripts/salib.py
SALib/test_functions/Ishigami.py
SALib/test_functions/Sobol_G.py
SALib/test_functions/__init__.py
SALib/test_functions/lake_problem.py
SALib/test_functions/linear_model_1.py
SALib/test_functions/linear_model_2.py
SALib/test_functions/oakley2004.py
SALib/test_functions/params/Ishigami.txt
SALib/test_functions/params/Ishigami_groups.txt
SALib/test_functions/params/Sobol_G.txt
SALib/util/__init__.py
SALib/util/problem.py
SALib/util/results.py
SALib/util/util_funcs.py
salib-1.5.0.dist-info/METADATA
salib-1.5.0.dist-info/WHEEL
salib-1.5.0.dist-info/entry_points.txt
salib-1.5.0.dist-info/licenses/AUTHORS.rst
salib-1.5.0.dist-info/licenses/LICENSE.md
salib-1.5.0.dist-info/RECORD
