Metadata-Version: 2.3
Name: SALib
Version: 1.5.0
Summary: Tools for global sensitivity analysis. Contains Sobol', Morris, FAST, DGSM, PAWN, HDMR, Moment Independent and fractional factorial methods
Project-URL: Documentation, https://salib.readthedocs.io
Project-URL: Source code, https://github.com/SALib/SALib
Author: Will Usher, Takuya Iwanaga
Author-email: Jon Herman <jdherman8@gmail.com>
Maintainer: SALib contributors
License-Expression: MIT
License-File: AUTHORS.rst
License-File: LICENSE.md
Classifier: Development Status :: 5 - Production/Stable
Classifier: Intended Audience :: Developers
Classifier: Intended Audience :: End Users/Desktop
Classifier: Intended Audience :: Science/Research
Classifier: License :: OSI Approved :: MIT License
Classifier: Operating System :: OS Independent
Classifier: Programming Language :: Python :: 3
Classifier: Programming Language :: Python :: 3.9
Classifier: Programming Language :: Python :: 3.10
Classifier: Programming Language :: Python :: 3.11
Classifier: Programming Language :: Python :: 3.12
Requires-Python: >=3.9
Requires-Dist: matplotlib>=3.5
Requires-Dist: multiprocess
Requires-Dist: numpy>=1.20.3
Requires-Dist: pandas>=2.0
Requires-Dist: scipy>=1.9.3
Provides-Extra: dev
Requires-Dist: hatch; extra == 'dev'
Requires-Dist: myst-parser; extra == 'dev'
Requires-Dist: numpydoc; extra == 'dev'
Requires-Dist: pathos>=0.3.2; extra == 'dev'
Requires-Dist: pre-commit; extra == 'dev'
Requires-Dist: pydata-sphinx-theme>=0.15.2; extra == 'dev'
Requires-Dist: pytest; extra == 'dev'
Requires-Dist: pytest-cov; extra == 'dev'
Requires-Dist: sphinx; extra == 'dev'
Provides-Extra: distributed
Requires-Dist: pathos>=0.3.2; extra == 'distributed'
Provides-Extra: doc
Requires-Dist: myst-parser; extra == 'doc'
Requires-Dist: numpydoc; extra == 'doc'
Requires-Dist: pydata-sphinx-theme>=0.15.2; extra == 'doc'
Requires-Dist: sphinx; extra == 'doc'
Provides-Extra: test
Requires-Dist: pathos>=0.3.2; extra == 'test'
Requires-Dist: pytest; extra == 'test'
Requires-Dist: pytest-cov; extra == 'test'
